LICENSE
MANIFEST.in
setup.py
Flask_RethinkDB.egg-info/PKG-INFO
Flask_RethinkDB.egg-info/SOURCES.txt
Flask_RethinkDB.egg-info/dependency_links.txt
Flask_RethinkDB.egg-info/not-zip-safe
Flask_RethinkDB.egg-info/requires.txt
Flask_RethinkDB.egg-info/top_level.txt
flask_rethinkdb/__init__.py
tests/__init__.py