Metadata-Version: 1.1
Name: Flask-RethinkDB
Version: 0.2
Summary: Adds RethinkDB support to Flask
Home-page: http://github.com/linkyndy/flask-rethinkdb
Author: Andrei Horak
Author-email: linkyndy@yahoo.com
License: MIT
Platform: any
Classifier: Environment :: Web Environment
Classifier: Intended Audience :: Developers
Classifier: License :: OSI Approved :: MIT License
Classifier: Operating System :: OS Independent
Classifier: Programming Language :: Python
Classifier: Topic :: Internet :: WWW/HTTP :: Dynamic Content
Classifier: Topic :: Software Development :: Libraries :: Python Modules
